README.rst
setup.py
flask_login_dictabase_blueprint/__init__.py
flask_login_dictabase_blueprint/menu.py
flask_login_dictabase_blueprint.egg-info/PKG-INFO
flask_login_dictabase_blueprint.egg-info/SOURCES.txt
flask_login_dictabase_blueprint.egg-info/dependency_links.txt
flask_login_dictabase_blueprint.egg-info/requires.txt
flask_login_dictabase_blueprint.egg-info/top_level.txt