Metadata-Version: 2.1
Name: flask_login_dictabase_blueprint
Version: 2.0.3
Summary: A Flask Blueprint for managing users.
Home-page: https://github.com/GrantGMiller/blueprint_flask_login_dictabase
Author: Grant miller
Author-email: grant@grant-miller.com
License: PSF
Project-URL: Source Code, https://github.com/GrantGMiller/blueprint_flask_login_dictabase
Keywords: grant miller flask blueprint dictabase login user management
Requires-Dist: flask
Requires-Dist: flask-dictabase
Requires-Dist: flask-login
